modfinder/__init__.py
modfinder/__main__.py
modfinder/downloader.py
modfinder/installer.py
modfinder-0.2.0.dist-info/METADATA
modfinder-0.2.0.dist-info/WHEEL
modfinder-0.2.0.dist-info/entry_points.txt
modfinder-0.2.0.dist-info/top_level.txt
modfinder-0.2.0.dist-info/RECORD
