Metadata-Version: 2.4
Name: modfinder
Version: 0.2.0
Summary: A Python-native module installer and CLI tool that installs packages without pip.
Author-email: Renee <caseysmail0715@gmail.com>
License: MIT
Project-URL: Homepage, https://github.com/Caseymaill/modfinder
Project-URL: Repository, https://github.com/Caseymaill/modfinder
Project-URL: PyPI, https://pypi.org/project/modfinder-renee
Requires-Python: >=3.7
Requires-Dist: requests
